difftree/main.py
difftree-0.1.1.dist-info/entry_points.txt
difftree-0.1.1.dist-info/WHEEL
difftree-0.1.1.dist-info/METADATA
difftree-0.1.1.dist-info/RECORD
