Metadata-Version: 2.1
Name: difftree
Version: 0.1.1
Summary: Diff two directories recursively
Home-page: https://github.com/malthejorgensen/difftree
License: MIT
Author: Malthe Jørgensen
Author-email: malthe.jorgensen@gmail.com
Requires-Python: >=3.7,<4.0
Classifier: Development Status :: 2 - Pre-Alpha
Classifier: Environment :: Console
Classifier: Intended Audience :: Developers
Classifier: Intended Audience :: System Administrators
Classifier: License :: OSI Approved :: MIT License
Classifier: Operating System :: OS Independent
Classifier: Programming Language :: Python :: 3
Classifier: Programming Language :: Python :: 3.10
Classifier: Programming Language :: Python :: 3.7
Classifier: Programming Language :: Python :: 3.8
Classifier: Programming Language :: Python :: 3.9
Classifier: Topic :: System :: Archiving :: Mirroring
Classifier: Topic :: System :: Filesystems
Classifier: Topic :: System :: Recovery Tools
Classifier: Topic :: Utilities
Project-URL: Repository, https://github.com/malthejorgensen/difftree
